example_fgen_basic-0.1.9.dist-info/METADATA
example_fgen_basic-0.1.9.dist-info/WHEEL
example_fgen_basic/_lib.cp312-win_arm64.pyd
example_fgen_basic/_lib.cp312-win_arm64.lib
example_fgen_basic/__init__.py
example_fgen_basic/exceptions.py
example_fgen_basic/get_wavelength.py
example_fgen_basic/operations.py
example_fgen_basic/runtime_helpers.py
example_fgen_basic-0.1.9.dist-info/RECORD
