Metadata-Version: 2.1
Name: example-fgen-basic
Version: 0.1.9
Summary: Basic example of using fgen
Author-Email: Zebedee Nicholls <zebedee.nicholls@climate-energy-college.org>
License: 3-Clause BSD License
Classifier: Development Status :: 3 - Alpha
Classifier: Intended Audience :: Science/Research
Classifier: License :: OSI Approved :: BSD License
Classifier: Natural Language :: English
Classifier: Operating System :: OS Independent
Classifier: Programming Language :: Python
Classifier: Programming Language :: Python :: 3
Classifier: Programming Language :: Python :: 3 :: Only
Classifier: Programming Language :: Python :: 3.9
Classifier: Programming Language :: Python :: 3.10
Classifier: Programming Language :: Python :: 3.11
Classifier: Programming Language :: Python :: 3.12
Classifier: Programming Language :: Python :: 3.13
Classifier: Typing :: Typed
Project-URL: Homepage, https://example-fgen-basic.readthedocs.io
Project-URL: Documentation, https://example-fgen-basic.readthedocs.io
Project-URL: Changelog, https://example-fgen-basic.readthedocs.io/en/stable/changelog
Project-URL: Repository, https://github.com/openscm/example-fgen-basic
Project-URL: Issues, https://github.com/openscm/example-fgen-basic/issues
Requires-Python: >=3.9
Requires-Dist: attrs>=24.3.0
Requires-Dist: numpy>=1.26.0; python_version < "3.13"
Requires-Dist: numpy>=2.1.0; python_version >= "3.13"
Requires-Dist: typing-extensions>=4.12.2
Provides-Extra: plots
Requires-Dist: matplotlib>=3.7.1; extra == "plots"
Provides-Extra: full
Requires-Dist: example-fgen-basic[plots]; extra == "full"
Provides-Extra: locked
Requires-Dist: attrs==25.3.0; extra == "locked"
Requires-Dist: numpy==2.0.2; python_full_version < "3.10" and extra == "locked"
Requires-Dist: numpy==2.2.6; python_full_version == "3.10.*" and extra == "locked"
Requires-Dist: numpy==2.3.2; python_full_version >= "3.11" and extra == "locked"
Requires-Dist: typing-extensions==4.12.2; extra == "locked"
Provides-Extra: plots-locked
Requires-Dist: attrs==25.3.0; extra == "plots-locked"
Requires-Dist: contourpy==1.3.0; python_full_version < "3.10" and extra == "plots-locked"
Requires-Dist: contourpy==1.3.2; python_full_version == "3.10.*" and extra == "plots-locked"
Requires-Dist: contourpy==1.3.3; python_full_version >= "3.11" and extra == "plots-locked"
Requires-Dist: cycler==0.12.1; extra == "plots-locked"
Requires-Dist: fonttools==4.59.0; extra == "plots-locked"
Requires-Dist: importlib-resources==6.5.2; python_full_version < "3.10" and extra == "plots-locked"
Requires-Dist: kiwisolver==1.4.7; python_full_version < "3.10" and extra == "plots-locked"
Requires-Dist: kiwisolver==1.4.9; python_full_version >= "3.10" and extra == "plots-locked"
Requires-Dist: matplotlib==3.9.4; python_full_version < "3.10" and extra == "plots-locked"
Requires-Dist: matplotlib==3.10.5; python_full_version >= "3.10" and extra == "plots-locked"
Requires-Dist: numpy==2.0.2; python_full_version < "3.10" and extra == "plots-locked"
Requires-Dist: numpy==2.2.6; python_full_version == "3.10.*" and extra == "plots-locked"
Requires-Dist: numpy==2.3.2; python_full_version >= "3.11" and extra == "plots-locked"
Requires-Dist: packaging==24.2; extra == "plots-locked"
Requires-Dist: pillow==11.3.0; extra == "plots-locked"
Requires-Dist: pyparsing==3.2.3; extra == "plots-locked"
Requires-Dist: python-dateutil==2.9.0.post0; extra == "plots-locked"
Requires-Dist: six==1.17.0; extra == "plots-locked"
Requires-Dist: typing-extensions==4.12.2; extra == "plots-locked"
Requires-Dist: zipp==3.23.0; python_full_version < "3.10" and extra == "plots-locked"
Provides-Extra: full-locked
Requires-Dist: attrs==25.3.0; extra == "full-locked"
Requires-Dist: contourpy==1.3.0; python_full_version < "3.10" and extra == "full-locked"
Requires-Dist: contourpy==1.3.2; python_full_version == "3.10.*" and extra == "full-locked"
Requires-Dist: contourpy==1.3.3; python_full_version >= "3.11" and extra == "full-locked"
Requires-Dist: cycler==0.12.1; extra == "full-locked"
Requires-Dist: fonttools==4.59.0; extra == "full-locked"
Requires-Dist: importlib-resources==6.5.2; python_full_version < "3.10" and extra == "full-locked"
Requires-Dist: kiwisolver==1.4.7; python_full_version < "3.10" and extra == "full-locked"
Requires-Dist: kiwisolver==1.4.9; python_full_version >= "3.10" and extra == "full-locked"
Requires-Dist: matplotlib==3.9.4; python_full_version < "3.10" and extra == "full-locked"
Requires-Dist: matplotlib==3.10.5; python_full_version >= "3.10" and extra == "full-locked"
Requires-Dist: numpy==2.0.2; python_full_version < "3.10" and extra == "full-locked"
Requires-Dist: numpy==2.2.6; python_full_version == "3.10.*" and extra == "full-locked"
Requires-Dist: numpy==2.3.2; python_full_version >= "3.11" and extra == "full-locked"
Requires-Dist: packaging==24.2; extra == "full-locked"
Requires-Dist: pillow==11.3.0; extra == "full-locked"
Requires-Dist: pyparsing==3.2.3; extra == "full-locked"
Requires-Dist: python-dateutil==2.9.0.post0; extra == "full-locked"
Requires-Dist: six==1.17.0; extra == "full-locked"
Requires-Dist: typing-extensions==4.12.2; extra == "full-locked"
Requires-Dist: zipp==3.23.0; python_full_version < "3.10" and extra == "full-locked"
